jupyter_status/__init__.py
jupyter_status/jupyter_status.py
Jupyter_Status-0.11.dist-info/LICENSE
Jupyter_Status-0.11.dist-info/METADATA
Jupyter_Status-0.11.dist-info/WHEEL
Jupyter_Status-0.11.dist-info/entry_points.txt
Jupyter_Status-0.11.dist-info/top_level.txt
Jupyter_Status-0.11.dist-info/RECORD
