Metadata-Version: 2.1
Name: Jupyter-Status
Version: 0.11
Summary: A quick, tabular summary of running Jupyter servers and kernels
Home-page: https://github.com/bagrow/jupyter-status
Author: Jim Bagrow
Author-email: bagrowjp@gmail.com
License: UNKNOWN
Platform: UNKNOWN
Classifier: Programming Language :: Python :: 3
Classifier: License :: OSI Approved :: BSD License
Classifier: Operating System :: OS Independent
Requires-Python: >=3.6
Requires-Dist: requests
Requires-Dist: tabulate
